setup.py
Dockets.egg-info/PKG-INFO
Dockets.egg-info/SOURCES.txt
Dockets.egg-info/dependency_links.txt
Dockets.egg-info/requires.txt
Dockets.egg-info/top_level.txt
dockets/__init__.py
dockets/docket.py
dockets/error_queue.py
dockets/errors.py
dockets/json_serializer.py
dockets/logging_event_handler.py
dockets/metadata.py
dockets/pipeline.py
dockets/queue.py
dockets/queue_event_registrar.py
dockets/redis_compatibility.py
dockets/stat_gatherer.py
dockets/lua/move_delayed_items.lua