Metadata-Version: 1.0
Name: Dockets
Version: 0.4.1
Summary: SUPER simple Redis-backed queueing in Python
Home-page: http://github.com/gamechanger/dockets
Author: Doug Woos
Author-email: doug@gamechanger.io
License: BSD
Keywords: redis queue schedule
Platform: UNKNOWN
